{"id": 9995, "text": "Sebastian Grammas\nsgrammas10@gmail.com | 410-212-0874\nRelevant Experience\nSoftware Engineer Intern \u2014 ALQIMI Technology Solutions (Rockville, MD) May\u2013Aug 2024, 2025\n\u2022 Delivered production-ready conversational AI features adopted for client-facing use, converting static\ndocuments and images into interactive, searchable insights.\n\u2022 Designed and shipped ALQIMI Assistant, a document-centric chat platform enabling natural\nlanguage Q&A over PDFs and images using semantic search and retrieval workflows.\n\u2022 Extended multimodal capabilities by integrating license plate recognition, OCR text extraction,\nand analog/digital clock detection to unify computer vision with chat-based UX.\n\u2022 Built a Visa demand forecasting pipeline (ARIMA/SARIMA/Prophet/LSTM) incorporating\nmacroeconomic signals (e.g., unemployment, changes in tech job demands) to improve\nissuance trend prediction.\n\u2022 Automated ingestion of web-scraped PDFs and metadata into Elasticsearch-backed search; optimized Vega\ndashboards and anomaly ranking via relevance/frequency scoring experiments.\nTechnical Founder / Lead Software Engineer \u2014 Solverah (Open Source) 2025\u2013Present\n\u2022 Building a job-matching and career-profiling platform using React + TypeScript + HTML frontend and Flask +\nPython APIs, with a focus on vertical AI agents for personalized recommendations.\n\u2022 Implemented structured profile and resume intake workflows and backend services to support scalable\nsimilarity scoring and future model training on user/job representations.\n\u2022 Designed deployment-ready architecture with cloud storage integration for uploaded resumes\nand artifacts, emphasizing reliability and low-latency user experiences.\nMachine Learning Engineer \u2014 FireNet (Academic Project) 2025\n\u2022 Implemented a U-Net-based segmentation model to predict next-day wildfire spread from geospatial inputs;\ndeveloped training/inference code and evaluation workflows.\n\u2022 Engineered dataset preprocessing and experiment tracking to benchmark model performance and\niterate on architecture and loss configurations.\nRelevant Skills\nFull-Stack: React, TypeScript, HTML/CSS, Flask, Python, REST APIs\nAI/ML: Conversational AI, semantic search, OCR, object detection, time-series\nforecasting (ARIMA/SARIMA/Prophet/LSTM), U-Net segmentation\nData: Web scraping, NiFi pipelines, Elasticsearch, dashboarding (Vega)\nSecurity: Modern Binary Exploitation (ROP, reverse engineering, mitigations), network security fundamentals\nLanguages: Python, C++, C, JavaScript, Assembly\nEducation\nRensselaer Polytechnic Institute (RPI), Troy, NY B.S. Computer Science\nExpected May 2026 | GPA 3.2\n\u2022 Concentration: Systems & Software | Minor: Economics\n\u2022 Scholarships: Rensselaer Recognition Scholarship; Rensselaer Leadership Scholarship\n\u2022 Activities: NCAA Soccer; Pi Kappa Alpha Fraternity (Recruitment Officer)\nAdditional\nISC2 Certified in Cybersecurity (CC) | Top 500 National Cyber League | Open-source contributor (Easy\nArtistry, CareerMatch AI)", "state": " MD", "resume_key": 9995, "dataset_version": "v1", "years_experience": 1, "education": "Rensselaer Polytechnic Institute (RPI), Troy, NY B.S. Computer Science Expected May 2026 | GPA 3.2", "skills": ["React", "TypeScript", "HTML", "CSS", "Flask", "Python", "REST APIs", "Conversational AI", "semantic search", "OCR", "object detection", "time-series", "forecasting", "ARIMA", "SARIMA", "Prophet", "LSTM", "U-Net segmentation", "Web scraping", "NiFi pipelines", "Elasticsearch", "dashboarding (Vega)", "Modern Binary Exploitation", "ROP", "reverse engineering", "mitigations", "network security fundamentals", "C++", "JavaScript", "Assembly"], "skills_by_category": {"Full-Stack": ["React", "TypeScript", "HTML", "CSS", "Flask", "Python", "REST APIs"], "AI/ML": ["Conversational AI", "semantic search", "OCR", "object detection", "time-series", "forecasting", "ARIMA", "SARIMA", "Prophet", "LSTM", "U-Net segmentation"], "Data": ["Web scraping", "NiFi pipelines", "Elasticsearch", "dashboarding (Vega)"], "Security": ["Modern Binary Exploitation", "ROP", "reverse engineering", "mitigations", "network security fundamentals"], "Languages": ["Python", "C++", "JavaScript", "Assembly"]}, "experience": [{"title": "Software Engineer Intern", "company": "ALQIMI Technology Solutions (Rockville", "duration": "Aug 2024", "impact_bullets": ["Delivered production-ready conversational AI features adopted for client-facing use, converting static documents and images into interactive, searchable insights.", "Designed and shipped ALQIMI Assistant, a document-centric chat platform enabling natural language Q&A over PDFs and images using semantic search and retrieval workflows.", "Extended multimodal capabilities by integrating license plate recognition, OCR text extraction, and analog/digital clock detection to unify computer vision with chat-based UX.", "Built a Visa demand forecasting pipeline (ARIMA/SARIMA/Prophet/LSTM) incorporating macroeconomic signals (e.g., unemployment, changes in tech job demands) to improve issuance trend prediction.", "Automated ingestion of web-scraped PDFs and metadata into Elasticsearch-backed search; optimized Vega dashboards and anomaly ranking via relevance/frequency scoring experiments."]}, {"title": "Technical Founder / Lead Software Engineer", "company": "Solverah (Open Source)", "duration": "2025-Present", "impact_bullets": ["Building a job-matching and career-profiling platform using React + TypeScript + HTML frontend and Flask + Python APIs, with a focus on vertical AI agents for personalized recommendations.", "Implemented structured profile and resume intake workflows and backend services to support scalable similarity scoring and future model training on user/job representations.", "Designed deployment-ready architecture with cloud storage integration for uploaded resumes and artifacts, emphasizing reliability and low-latency user experiences. Machine Learning Engineer - FireNet (Academic Project) 2025", "Implemented a U-Net-based segmentation model to predict next-day wildfire spread from geospatial inputs; developed training/inference code and evaluation workflows.", "Engineered dataset preprocessing and experiment tracking to benchmark model performance and iterate on architecture and loss configurations."]}], "projects": [], "certifications": [], "clearances_or_work_auth": ""}
{"id": 9996, "text": "MICHAEL R. TURNER | CPCU, ARM\nClaims \u2022 Risk \u2022 Compliance | michael.turner@email.com | 555-321-7788 | Hartford, CT\nBackground: Insurance professional with experience spanning claims adjustment, underwriting support, and\nregulatory compliance. Known for cross-functional coordination, loss analysis, and policy interpretation.\nCore Competencies \u2014 Claims Investigation; Policy Interpretation; Loss Mitigation; Regulatory Reporting;\nCustomer Escalations; Risk Analysis; Documentation Review\nWork History\nSenior Claims Analyst (2018\u2013Present)\nNortheast Mutual Insurance Group, Hartford CT\n- Lead complex commercial property and casualty claims exceeding $500K\n- Interpret policy language to determine coverage and exclusions\n- Coordinate with legal counsel, adjusters, and external investigators\nClaims Adjuster | 2014\u20132018\nPioneer Assurance Co.\n- Conducted on-site and desk claim investigations\n- Prepared loss summaries and settlement recommendations\n- Maintained compliance with state insurance regulations\nEducation & Training\nB.A. Economics \u2014 Central Connecticut State University (2013)\nContinuing Education: Insurance Law Updates, Fraud Detection Workshops\nCredentials: Chartered Property Casualty Underwriter (CPCU); Associate in Risk Management (ARM); State of\nConnecticut Licensed Claims Adjuster\nSystems exposure includes Guidewire ClaimCenter, Duck Creek, ISO ClaimSearch, Microsoft Excel (loss\nmodeling), internal policy management platforms.\nOther Notes\nEligible to work in the U.S. without sponsorship. Available for hybrid or remote roles. Professional interests include\ninsurance technology modernization and claims automation.", "state": " NY", "resume_key": 9996, "dataset_version": "v1", "years_experience": 12, "education": "B.A. Economics - Central Connecticut State University (2013) Continuing Education: Insurance Law Updates, Fraud Detection Workshops", "skills": [], "skills_by_category": {}, "experience": [{"title": "Senior Claims Analyst", "company": "Northeast Mutual Insurance Group", "duration": "2018-Present", "impact_bullets": ["Lead complex commercial property and casualty claims exceeding $500K", "Interpret policy language to determine coverage and exclusions", "Coordinate with legal counsel, adjusters, and external investigators"]}, {"title": "Claims Adjuster", "company": "Pioneer Assurance Co.", "duration": "2014-2018", "impact_bullets": ["Conducted on-site and desk claim investigations", "Prepared loss summaries and settlement recommendations", "Maintained compliance with state insurance regulations"]}], "projects": [], "certifications": ["Chartered Property Casualty Underwriter (CPCU)", "Associate in Risk Management (ARM)", "State of Connecticut Licensed Claims Adjuster Systems exposure includes Guidewire ClaimCenter", "Duck Creek", "ISO ClaimSearch", "Microsoft Excel (loss modeling)", "internal policy management platforms. Other Notes Eligible to work in the U.S. without sponsorship. Available for hybrid or remote roles. Professional interests include insurance technology modernization", "claims automation"], "clearances_or_work_auth": ""}
{"id": 9997, "text": "JANE M. SMITH, RN, BSN\nRegistered Nurse | Clinical Care | Patient Advocacy\nEmail: jane.smith@example.com\nPhone: (555) 987-6543\nLocation: Chicago, IL, USA\nLinkedIn: https://www.linkedin.com/in/janesmith-rn\nPROFESSIONAL SUMMARY\nCompassionate Registered Nurse with 7+ years of experience providing high-quality patient care in\nacute care and outpatient clinical settings. Proven ability to collaborate with multidisciplinary healthcare\nteams, manage complex patient cases, and ensure compliance with healthcare regulations and patient\nsafety standards.\nCLINICAL SKILLS\nPatient Care: Patient Assessment, Care Planning, Vital Signs Monitoring, Medication Administration\nClinical Procedures: IV Therapy, Wound Care, Catheterization, Infection Control\nHealthcare Systems: Electronic Health Records (Epic, Cerner), Clinical Documentation\nCompliance & Safety: HIPAA Compliance, Patient Privacy, Risk Management\nPROFESSIONAL EXPERIENCE\nREGISTERED NURSE\nMercy General Hospital \u2014 Chicago, IL\nMarch 2019 \u2013 Present\n- Provide direct patient care for medical-surgical and post-operative patients\n- Administer medications and monitor patient responses to treatment\n- Coordinate care with physicians, specialists, and allied health professionals\n- Maintain accurate clinical documentation within EHR systems\nCLINICAL NURSE\nLakeside Family Health Clinic \u2014 Evanston, IL\nJune 2016 \u2013 February 2019\n- Assisted physicians during examinations and minor procedures\n- Educated patients on treatment plans, medications, and preventative care\n- Managed appointment scheduling and follow-up care coordination\nEDUCATION\nBACHELOR OF SCIENCE IN NURSING (BSN)\nUniversity of Illinois at Chicago \u2014 Chicago, IL\nGraduated: May 2016\nLICENSURE & CERTIFICATIONS\nRegistered Nurse (RN) \u2014 State of Illinois\nBasic Life Support (BLS) Certification\nAdvanced Cardiac Life Support (ACLS) Certification\n\nVOLUNTEER EXPERIENCE\nCOMMUNITY HEALTH VOLUNTEER\nChicago Free Health Clinic\n- Provided basic health screenings and patient education services\nADDITIONAL INFORMATION\nWork Authorization: Authorized to work in the United States\nLanguages: English (Native), Polish (Conversational)\nProfessional Interests: Patient Advocacy, Community Health, Healthcare Quality Improvement", "state": " CA", "resume_key": 9997, "dataset_version": "v1", "years_experience": 7, "education": "BACHELOR OF SCIENCE IN NURSING (BSN) University of Illinois at Chicago - Chicago, IL\nUniversity of Illinois at Chicago - Chicago, IL Graduated: May 2016", "skills": ["Patient Assessment", "Care Planning", "Vital Signs Monitoring", "Medication Administration", "IV Therapy", "Wound Care", "Catheterization", "Infection Control", "Electronic Health Records", "Epic", "Cerner", "Clinical Documentation", "HIPAA Compliance", "Patient Privacy", "Risk Management"], "skills_by_category": {"Patient Care": ["Patient Assessment", "Care Planning", "Vital Signs Monitoring", "Medication Administration"], "Clinical Procedures": ["IV Therapy", "Wound Care", "Catheterization", "Infection Control"], "Healthcare Systems": ["Electronic Health Records", "Epic", "Cerner", "Clinical Documentation"], "Compliance & Safety": ["HIPAA Compliance", "Patient Privacy", "Risk Management"]}, "experience": [{"title": "Registered Nurse", "company": "Mercy General Hospital - Chicago", "duration": "March 2019 - Present", "impact_bullets": ["Provide direct patient care for medical-surgical and post-operative patients", "Administer medications and monitor patient responses to treatment", "Coordinate care with physicians, specialists, and allied health professionals", "Maintain accurate clinical documentation within EHR systems"]}, {"title": "Clinical Nurse", "company": "Lakeside Family Health Clinic - Evanston", "duration": "June 2016 - February 2019", "impact_bullets": ["Assisted physicians during examinations and minor procedures", "Educated patients on treatment plans, medications, and preventative care", "Managed appointment scheduling and follow-up care coordination"]}, {"title": "COMMUNITY HEALTH VOLUNTEER", "company": "Chicago Free Health Clinic", "duration": "", "impact_bullets": ["Provided basic health screenings and patient education services"]}], "projects": [], "certifications": ["Registered Nurse (RN) - State of Illinois", "Basic Life Support (BLS) Certification", "Advanced Cardiac Life Support (ACLS) Certification"], "clearances_or_work_auth": "Work Authorization"}
{"id": 9998, "text": "JOHN A. DOE\nSoftware Engineer | Machine Learning | Data Systems\nEmail: john.doe@example.com\nPhone: (555) 123-4567\nLocation: Boston, MA, USA\nLinkedIn: https://www.linkedin.com/in/johndoe\nGitHub: https://github.com/johndoe\nPROFESSIONAL SUMMARY\nResults-driven Software Engineer with 5+ years of experience building scalable backend systems,\nmachine learning pipelines, and data-driven applications. Strong background in Python, distributed\nsystems, and applied NLP. Experienced working in cross-functional teams and delivering\nproduction-ready solutions.\nTECHNICAL SKILLS\nProgramming Languages: Python, Java, C++, JavaScript, SQL\nFrameworks & Libraries: Flask, FastAPI, React, TensorFlow, PyTorch, scikit-learn\nData & ML: Natural Language Processing (NLP), Feature Engineering, Model Evaluation, ETL\nPipelines\nDatabases: PostgreSQL, MySQL, MongoDB, Redis\nCloud & DevOps: AWS (EC2, S3, Lambda), Docker, GitHub Actions, Linux\nPROFESSIONAL EXPERIENCE\nSOFTWARE ENGINEER\nAcme Technologies Inc. \u2014 New York, NY\nJune 2021 \u2013 Present\n- Designed and implemented REST APIs using Flask and FastAPI serving over 1M requests/day\n- Built NLP pipelines to extract structured data from unstructured documents (resumes, PDFs)\n- Improved system performance by 35% through query optimization and caching strategies\n- Collaborated with product managers and designers in an Agile environment\nJUNIOR SOFTWARE ENGINEER\nBeta Analytics LLC \u2014 Remote\nJuly 2019 \u2013 May 2021\n- Developed data ingestion pipelines for analytics dashboards\n- Assisted in training and evaluating machine learning models for classification tasks\n- Wrote unit and integration tests to improve code reliability\n- Participated in code reviews and sprint planning\nEDUCATION\n\nBACHELOR OF SCIENCE IN COMPUTER SCIENCE\nUniversity of Example \u2014 Example City, State\nGraduated: May 2019\nRelevant Coursework: Data Structures, Algorithms, Databases, Machine Learning, Operating Systems\nPROJECTS\nRESUME PARSING ENGINE\nBuilt a resume parsing tool to extract skills, experience, and education using spaCy and custom\nrule-based heuristics. Achieved 92% accuracy on labeled test resumes.\nRECOMMENDATION SYSTEM\nImplemented collaborative filtering and content-based recommendation models and deployed models\nusing Docker and AWS.\nCERTIFICATIONS\nAWS Certified Solutions Architect \u2013 Associate\nGoogle Data Analytics Certificate\nPUBLICATIONS\nDoe, J. (2022). Automated Information Extraction from Unstructured Resumes. Journal of Applied\nMachine Learning\nVOLUNTEER EXPERIENCE\nTECHNICAL MENTOR\nCode for Good Initiative\nMentored junior developers in Python and web development fundamentals\nADDITIONAL INFORMATION\nWork Authorization: Authorized to work in the United States\nLanguages: English (Native), Spanish (Conversational)\nInterests: Machine Learning, Open-Source Software, Technical Writing", "state": " TX", "resume_key": 9998, "dataset_version": "v1", "years_experience": 5, "education": "BACHELOR OF SCIENCE IN COMPUTER SCIENCE University of Example - Example City, State\nUniversity of Example - Example City, State Graduated: May 2019", "skills": ["Python", "Java", "C++", "JavaScript", "SQL", "Flask", "FastAPI", "React", "TensorFlow", "PyTorch", "scikit-learn", "Natural Language Processing (NLP)", "Feature Engineering", "Model Evaluation", "ETL", "Pipelines", "PostgreSQL", "MySQL", "MongoDB", "Redis", "AWS", "EC2", "S3", "Lambda", "Docker", "GitHub Actions", "Linux"], "skills_by_category": {"Programming Languages": ["Python", "Java", "C++", "JavaScript", "SQL"], "Frameworks & Libraries": ["Flask", "FastAPI", "React", "TensorFlow", "PyTorch", "scikit-learn"], "Data & ML": ["Natural Language Processing (NLP)", "Feature Engineering", "Model Evaluation", "ETL", "Pipelines"], "Databases": ["PostgreSQL", "MySQL", "MongoDB", "Redis"], "Cloud & DevOps": ["AWS", "EC2", "S3", "Lambda", "Docker", "GitHub Actions", "Linux"]}, "experience": [{"title": "Software Engineer", "company": "Acme Technologies Inc. - New York", "duration": "June 2021 - Present", "impact_bullets": ["Designed and implemented REST APIs using Flask and FastAPI serving over 1M requests/day", "Built NLP pipelines to extract structured data from unstructured documents (resumes, PDFs)", "Improved system performance by 35% through query optimization and caching strategies", "Collaborated with product managers and designers in an Agile environment"]}, {"title": "Junior Software Engineer", "company": "Beta Analytics LLC", "duration": "July 2019 - May 2021", "impact_bullets": ["Developed data ingestion pipelines for analytics dashboards", "Assisted in training and evaluating machine learning models for classification tasks", "Wrote unit and integration tests to improve code reliability", "Participated in code reviews and sprint planning"]}, {"title": "TECHNICAL MENTOR", "company": "Code for Good Initiative", "duration": "", "impact_bullets": ["Mentored junior developers in Python and web development fundamentals"]}], "projects": ["RESUME PARSING ENGINE", "Built a resume parsing tool to extract skills, experience, and education using spaCy and custom", "rule-based heuristics. Achieved 92% accuracy on labeled test resumes.", "RECOMMENDATION SYSTEM", "Implemented collaborative filtering and content-based recommendation models and deployed models", "using Docker and AWS."], "certifications": ["AWS Certified Solutions Architect - Associate", "Google Data Analytics Certificate"], "clearances_or_work_auth": "Work Authorization"}
{"id": 9994, "text": "LW\nLaura Wusthoff\nSan Diego, CA 92115\n(973) 563-0591\nlaura.wusthoff@gmail.com\nPROFESSIONAL\nSUMMARY\nSeasoned Media professional with comprehensive performance media\nexperience. Collaborative and analytical with a data-focused mindset. Skilled at\nbudget management and platform testing, always with a finger on the pulse of\nemerging trends and technologies.\nSKILLS\nOmni-Channel Media Strategy\nProfitability Analysis\nKPI Creation\nPerformance Testing and\nOptimization\nData Analysis\nPaid Media Platforms\nWORK HISTORY\n08/2020 to CURRENT\nSR. DIRECTOR OF MEDIA\n85SIXTY | San Diego, CA\nDevelop cross-channel marketing strategy and for priority clients that drive\nengagement, conversion and retention with continuous refinement for\nincreased performance\nAssist clients with pivoting business plans to offset Covid impacts and\ncapitalize on emerging opportunities\nCreate KPI frameworks for clients that allow for performance gains,\nsupporting current and long term growth plans\nEnsure that brands are meeting performance forecasts, utilizing platform\nand site data to optimize media strategy\n02/2019 to 08/2020\nMEDIA DIRECTOR\nBVA | San Diego, CA\nOversaw Paid Search, Paid Social, Display, and Affiliate teams with over\n$2.5MM in monthly spend\nCreated go-to-market strategies for net new brands while forecasting initial\nand long term returns for LTV, CAC, CPA and ROAS\nOwned strategy for largest clients and KPI driven results for entire Media\nportfolio\nStreamlined cross-functional operations processes and workflow to\nincrease efficiency, performance and department profitability\n03/2018 to 02/2019\nDIRECTOR OF CLIENT STRATEGY\nKatana (Acquired By BVA) | San Diego, CA\nClient service lead for CPG and eCommerce clients leading\n\ncommunication, contract negotiations, and executive expectations\nEstablished profitability in client portfolio by balancing employee hours and\nclient fees\n05/2016 to 03/2018\nASSOCIATE MEDIA DIRECTOR\nKatana (Acquired By BVA) | San Diego, CA\nTroubleshot problem accounts, developed strategic media proposals and\npitched new business for Katana\nMaintained positive revenue growth and client retention within Media\ndepartment by overseeing daily workflow and quality of deliverables for\nseven person department\n04/2015 to 05/2016\nMEDIA SUPERVISOR\nKatana (Acquired By BVA) | San Diego, CA\nBuilt, executed and optimized media campaigns across programmatic\ndisplay, paid search and paid social platforms\nNormalized and aggregated large data sets to dissect key insights for\noptimization and strategy\n07/2012 to 04/2015\nSR. PAID MEDIA STRATEGIST\nIMI | San Diego, CA\nPlanned, bought and managed direct response media campaigns for\nagency's largest display accounts\nResearched new media partners and products to stay ahead of digital\ntrends\n08/2010 to 07/2012\nMEDIA MANAGER\nGreenhaus | San Diego, CA\nPlanned, optimized and negotiated combined traditional and online media\nbudgets including paid search and display media\n09/2008 to 04/2010\nDIGITAL MARKETING MANAGER\nThe Magna Group | Fair Lawn, NJ\nCreated and grew digital (Paid Search and Google Display) department for\ntraditional media agency\n01/2006 to 09/2008\nMEDIA BUYER\nThe Magna Group | Fair Lawn, NJ\nRan traditional media campaigns across TV, cable and radio by negotiating\nrates and building vendor relationships\nEDUCATION\n06/2005\nAssociate of Arts | Journalism And Media Studies\nRutgers, The State University of New Jersey, New Brunswick, NJ", "state": " CA", "resume_key": 9994, "dataset_version": "v1", "years_experience": 20, "education": "Associate of Arts | Journalism And Media Studies Rutgers, The State University of New Jersey, New Brunswick, NJ\nRutgers, The State University of New Jersey, New Brunswick, NJ", "skills": ["Omni-Channel Media Strategy", "Profitability Analysis", "KPI Creation", "Performance Testing and Optimization", "Data Analysis", "Paid Media Platforms"], "skills_by_category": {"Skills": ["Omni-Channel Media Strategy", "Profitability Analysis", "KPI Creation", "Performance Testing and Optimization", "Data Analysis", "Paid Media Platforms"]}, "experience": [{"title": "", "company": "SR. DIRECTOR OF MEDIA", "duration": "08/2020 to CURRENT", "impact_bullets": []}, {"title": "", "company": "MEDIA DIRECTOR", "duration": "02/2019 to 08/2020", "impact_bullets": []}, {"title": "", "company": "DIRECTOR OF CLIENT STRATEGY", "duration": "03/2018 to 02/2019", "impact_bullets": []}, {"title": "", "company": "ASSOCIATE MEDIA DIRECTOR", "duration": "05/2016 to 03/2018", "impact_bullets": []}, {"title": "", "company": "MEDIA SUPERVISOR", "duration": "04/2015 to 05/2016", "impact_bullets": []}, {"title": "Media Supervisor", "company": "SR. PAID MEDIA STRATEGIST", "duration": "07/2012 to 04/2015", "impact_bullets": []}, {"title": "Sr. Paid Media Strategist", "company": "MEDIA MANAGER", "duration": "08/2010 to 07/2012", "impact_bullets": []}, {"title": "Media Manager", "company": "DIGITAL MARKETING MANAGER", "duration": "09/2008 to 04/2010", "impact_bullets": []}, {"title": "Digital Marketing Manager", "company": "MEDIA BUYER", "duration": "01/2006 to 09/2008", "impact_bullets": []}], "projects": [], "certifications": [], "clearances_or_work_auth": ""}
{"id": 9993, "text": "Anne Taylor Murlowski\n13768 Josephine Ct. \u25cfThornton CO 80602 \u25cf(720)296-3302 \u25cfannemurlowski@gmail.com\nEducation\nColorado State University, Fort Collins, CO Majors: Technical Journalism & Liberal Arts\nSkills Summary\nExperienced in developing innovative marketing campaigns utilizing search engine optimization, paid media, marketing\nautomation, social media, email marketing and blogger outreach. Confident facilitator and corporate trainer.\nWell-versed in the use of: Agile Marketing, Account Based Marketing, Affiliate Marketing, Pardot, Marketo, Salesforce,\nSEMRush, Drift, Social Studio, Adobe Photoshop, Cision, Hootsuite, and Google Analytics.\nProfessional Experience\nSENIOR MANAGER, DIGITAL MARKETING\nSEPTEMBER 2020 - CURRENT\nConga\nBroomfield, CO\n\u25cf\nManaged paid media spend of $4M+ across SEM, Social, Content Syndication and Cost Per Lead Programs.\nAchieved target pipeline goals over consecutive quarters.\n\u25cf\nMaintained consistent brand messaging and paid media strategy across two divergent brands while undergoing\nmerger and acquisition processes to transition to a single brand.\n\u25cf\nOwned digital strategy including launch of new corporate website across multiple regions and languages.\n\u25cf\nCoached five direct reports including developing career paths and working collaboratively to exceed individual\ncontributor goals for the digital strategy team as a whole. Responsible for team hiring including working with\nexternal recruiting agencies to identify best-in-class candidates for open roles.\n\u25cf\nActivated global campaign initiatives by building and owning omni-channel digital media plans for corporate\nevents, lead generation and corporate sponsorships.\n\u25cf\nResponsible for all vendor relationships including RFP process for paid media programs and agency relationships.\nManaged contracting process working collaboratively with legal and purchasing.\nDIGITAL MARKETING STRATEGIST\nNOVEMBER 2019 - SEPTEMBER 2020\nScaled Agile\nBoulder, CO\n\u25cf\nExecuted go to market campaign for the launch of remote training products including refining segmentations and\nimplementing multi-touch communication channels. Increased established audience engagement by 101%.\n\u25cf\nDeveloped strategy and launched a comprehensive social listening campaign in collaboration with the Customer\nSuccess team to identify customer support tickets, legal and licensing violations, and sales opportunities.\n\u25cf\nCoordinated development of Marketo landing page template and owned landing page build outs.\n\u25cf\nImproved digital ad spend by implementing KPI tracking and refining campaign structures to target customer\npersonas and drive sales. Increased class registration using social media advertising.\n\u25cf\nSpearheaded channel marketing advertising strategy using influencer marketing tools to positively impact\npartner sales for global training providers, including campaigns in Ireland, India, and Australia.\n\u25cf\nChampioned SEO strategy including enabling keyword research and monthly search performance monitoring.\n\nDIRECTOR OF MARKETING\nAUGUST 2016 - NOVEMBER 2019\nMARKETING MANAGER\nAUGUST 2014 - AUGUST 2016\nSuiteHop\nDenver, CO\n\u25cf\nEstablished brand identity for a startup company to bring well-received brand voice and style to advertising,\nmedia relations and website messaging. Managed marketing strategy and budget.\n\u25cf\nBuilt a marketing team from the ground up, providing creative direction to in-house marketing staff and a team\nof external contractors responsible for producing marketing collateral including print, digital, public relations,\nvideo and SEO.\n\u25cf\nCreated CRM infrastructure (SalesForce) to produce marketing reporting dashboards. Calculated marketplace\nKPIs and ROAS. Analyzing sales data to evaluate customer trends and develop customer personas.\n\u25cf\nManaged omnichannel lead gen, including implementation of SEO, e-mail, radio, print, display, microsites\ninfluencer marketing, and direct mail. Overall marketing strategy resulted in consistent website traffic increase of\n45% annually and 330% annual increase in ecommerce transactions.\n\u25cf\nBuilt content marketing automation process including chatbots to generate marketing qualified leads.\nEstablished lead nurture and retention program. Developed strategies for increasing customer lifetime value and\nlowered acquisition costs using Account Based Marketing.\nSOCIAL MEDIA MANAGER\nMAY 2013 \u2013 AUGUST 2014\nShane Company\nDenver, CO\n\u25cf\nResponsible for strategy and implementation for the national footprint of Shane Co. social presence including\nFacebook, Twitter, Google+, Pinterest, Instagram, Yelp and other review sites.\n\u25cf\nManaged corporate blog team consisting of 21 local store contributors. Managed blog editorial timeline.\n\u25cf\nIncreased ROI on digital media spend by analyzing ad performance and optimizing spend.\n\u25cf\nExecuted local events plan for building community presence within Yelp Elite network.\n\u25cf\nManaged influencer marketing program and secured paid advertorial partnerships.\nCONTENT SPECIALIST\nJULY 2011 \u2013 MAY 2013\nA-Train Marketing Communications\nFort Collins, CO\n\u25cf\nResponsible for the development of digital marketing strategy, search engine optimization, social media strategy\nand training for all A-Train clientele.\n\u25cf\nAssisted with project management by developing project directions and relaying information, including creative\ndirection to design team and copywriters. Created content and tracked production timelines.\n\u25cf\nAttended milestone meetings and drove digital account strategy for top clients.\nMARKETING AND COMMUNICATIONS MANAGER\nAUGUST 2010 \u2013 JULY 2011\nCOMMUNICATIONS COORDINATOR\nFEBRUARY 2009 \u2013 AUGUST 2010\nDelta Delta Delta Fraternity\nArlington, TX\n\u25cf\nDeveloped a marketing plan for national campaign \u2018Fat Talk Free Week\u2019, an online cause-campaign reaching over\n88,000,000 viewers via TIME online, CNN, MSNBC, Huffington Post and countless blogs.\n\u25cf\nCreated content and tracked production timelines while coordinating the publication of e-newsletters for\nnationwide membership and volunteers.\n\u25cf\nDeveloped and implemented plans for social media engagement including use of Twitter, Facebook, LinkedIn and\nFlickr. Grew Twitter followers over 3,400 and Facebook over 10,000, in a 1 year period.\n\u25cf\nContent managed TriDelta.org and chapter extension websites including formal redesign.", "state": " CO", "resume_key": 9993, "dataset_version": "v1", "years_experience": 17, "education": "Colorado State University, Fort Collins, CO Majors: Technical Journalism & Liberal Arts", "skills": ["search engine optimization", "paid media", "marketing automation", "social media", "email marketing", "blogger outreach", "Agile Marketing", "Account Based Marketing", "Affiliate Marketing", "Pardot", "Marketo", "Salesforce", "SEMRush", "Drift", "Social Studio", "Adobe Photoshop", "Cision", "Hootsuite", "Google Analytics"], "skills_by_category": {"Skills": ["search engine optimization", "paid media", "marketing automation", "social media", "email marketing", "blogger outreach"], "Well-versed in the use of": ["Agile Marketing", "Account Based Marketing", "Affiliate Marketing", "Pardot", "Marketo", "Salesforce", "SEMRush", "Drift", "Social Studio", "Adobe Photoshop", "Cision", "Hootsuite", "Google Analytics"]}, "experience": [{"title": "Senior Manager, Digital Marketing", "company": "Conga", "duration": "SEPTEMBER 2020 - CURRENT", "impact_bullets": ["Broomfield, CO", "-", "Managed paid media spend of $4M+ across SEM, Social, Content Syndication and Cost Per Lead Programs.", "Achieved target pipeline goals over consecutive quarters.", "-", "Maintained consistent brand messaging and paid media strategy across two divergent brands while undergoing merger and acquisition processes to transition to a single brand.", "-", "Owned digital strategy including launch of new corporate website across multiple regions and languages.", "-", "Coached five direct reports including developing career paths and working collaboratively to exceed individual contributor goals for the digital strategy team as a whole. Responsible for team hiring including working with external recruiting agencies to identify best-in-class candidates for open roles.", "-", "Activated global campaign initiatives by building and owning omni-channel digital media plans for corporate events, lead generation and corporate sponsorships.", "-", "Responsible for all vendor relationships including RFP process for paid media programs and agency relationships.", "Managed contracting process working collaboratively with legal and purchasing."]}, {"title": "Digital Marketing Strategist", "company": "Scaled Agile", "duration": "NOVEMBER 2019 - SEPTEMBER 2020", "impact_bullets": ["Boulder, CO", "-", "Executed go to market campaign for the launch of remote training products including refining segmentations and implementing multi-touch communication channels. Increased established audience engagement by 101%.", "-", "Developed strategy and launched a comprehensive social listening campaign in collaboration with the Customer", "Success team to identify customer support tickets, legal and licensing violations, and sales opportunities.", "-", "Coordinated development of Marketo landing page template and owned landing page build outs.", "-", "Improved digital ad spend by implementing KPI tracking and refining campaign structures to target customer personas and drive sales. Increased class registration using social media advertising.", "-", "Spearheaded channel marketing advertising strategy using influencer marketing tools to positively impact partner sales for global training providers, including campaigns in Ireland, India, and Australia.", "-", "Championed SEO strategy including enabling keyword research and monthly search performance monitoring."]}, {"title": "Director Of Marketing", "company": "MARKETING MANAGER", "duration": "AUGUST 2016 - NOVEMBER 2019", "impact_bullets": []}, {"title": "Marketing Manager", "company": "SuiteHop", "duration": "AUGUST 2014 - AUGUST 2016", "impact_bullets": ["Denver, CO", "-", "Established brand identity for a startup company to bring well-received brand voice and style to advertising, media relations and website messaging. Managed marketing strategy and budget.", "-", "Built a marketing team from the ground up, providing creative direction to in-house marketing staff and a team of external contractors responsible for producing marketing collateral including print, digital, public relations, video and SEO.", "-", "Created CRM infrastructure (SalesForce) to produce marketing reporting dashboards. Calculated marketplace", "KPIs and ROAS. Analyzing sales data to evaluate customer trends and develop customer personas.", "-", "Managed omnichannel lead gen, including implementation of SEO, e-mail, radio, print, display, microsites influencer marketing, and direct mail. Overall marketing strategy resulted in consistent website traffic increase of", "45% annually and 330% annual increase in ecommerce transactions.", "-", "Built content marketing automation process including chatbots to generate marketing qualified leads.", "Established lead nurture and retention program. Developed strategies for increasing customer lifetime value and lowered acquisition costs using Account Based Marketing."]}, {"title": "Social Media Manager", "company": "Shane Company", "duration": "MAY 2013 - AUGUST 2014", "impact_bullets": ["Denver, CO", "-", "Responsible for strategy and implementation for the national footprint of Shane Co. social presence including", "Facebook, Twitter, Google+, Pinterest, Instagram, Yelp and other review sites.", "-", "Managed corporate blog team consisting of 21 local store contributors. Managed blog editorial timeline.", "-", "Increased ROI on digital media spend by analyzing ad performance and optimizing spend.", "-", "Executed local events plan for building community presence within Yelp Elite network.", "-", "Managed influencer marketing program and secured paid advertorial partnerships."]}, {"title": "Content Specialist", "company": "A-Train Marketing Communications", "duration": "JULY 2011 - MAY 2013", "impact_bullets": ["Fort Collins, CO", "-", "Responsible for the development of digital marketing strategy, search engine optimization, social media strategy and training for all A-Train clientele.", "-", "Assisted with project management by developing project directions and relaying information, including creative direction to design team and copywriters. Created content and tracked production timelines.", "-", "Attended milestone meetings and drove digital account strategy for top clients."]}, {"title": "Marketing And Communications Manager", "company": "COMMUNICATIONS COORDINATOR", "duration": "AUGUST 2010 - JULY 2011", "impact_bullets": []}, {"title": "Communications Coordinator", "company": "Delta Delta Delta Fraternity", "duration": "FEBRUARY 2009 - AUGUST 2010", "impact_bullets": ["Arlington, TX", "-", "Developed a marketing plan for national campaign \u2018Fat Talk Free Week\u2019, an online cause-campaign reaching over", "88,000,000 viewers via TIME online, CNN, MSNBC, Huffington Post and countless blogs.", "-", "Created content and tracked production timelines while coordinating the publication of e-newsletters for nationwide membership and volunteers.", "-", "Developed and implemented plans for social media engagement including use of Twitter, Facebook, LinkedIn and Flickr. Grew Twitter followers over 3,400 and Facebook over 10,000, in a 1 year period.", "-", "Content managed TriDelta.org and chapter extension websites including formal redesign."]}], "projects": [], "certifications": [], "clearances_or_work_auth": ""}
{"id": 9992, "text": "Sydney Grogg____________________________________________\n403 Belle Point Dr\n\nsgrogg70@gmail.com\n\nMt. Pleasant, 29464\n\n843.330.3524\n\nSeeking to expand my education in the healthcare field where I know I can excel\nin a professional environment and achieve my goals.\n\nExperience:\n\nCharleston County Schools \u2013 Belle Hall Kaleidoscope\n3/15-present\nAfter School/Summer Counselor\n\n- Supervise and interact with children\n- Prepare lesson plans\n- Coordinate daily summer activities and field trips\n\nPlay Garden\n\n12/14-3/15\nTeacher/Facilitator\n\n- Daily supervising and interaction with children of all ages\n- Arranged daily art, music, yoga, etc\u2026 activities\n- Managed and processed customers\n\nEducation:\n\nCoastal Christian Prepatory School\n\n8/08-5/13\n\nUniversity of South Carolina Beaufort\n\n8/13-12/14\n\nCollege of Charleston\n\n1/15-present\n\nPersonal Achievements:\n\nMember of the Phi Mu Fraternity\n\nHomecoming Queen of 2013\n\nVarsity Volleyball\n\nVarsity Cheerleading\n\nVarsity Basketball\n\nSkills:\n\nCPR certified\n\nFirst Aid certified", "state": " NA", "resume_key": 9992, "dataset_version": "v1", "years_experience": 11, "education": "Coastal Christian Prepatory School\nUniversity of South Carolina Beaufort\nCollege of Charleston", "skills": ["CPR certified", "First Aid certified"], "skills_by_category": {"Skills": ["CPR certified", "First Aid certified"]}, "experience": [{"title": "", "company": "After School/Summer Counselor", "duration": "3/15-present", "impact_bullets": ["Supervise and interact with children", "Prepare lesson plans", "Coordinate daily summer activities and field trips", "Play Garden"]}, {"title": "", "company": "Teacher/Facilitator", "duration": "12/14-3/15", "impact_bullets": ["Daily supervising and interaction with children of all ages", "Arranged daily art, music, yoga, etc\u2026 activities", "Managed and processed customers"]}], "projects": [], "certifications": [], "clearances_or_work_auth": ""}
{"id": 9991, "text": "NATALIE ROSS\nN\nR\nNatRoss14@gmail.com\n314.566.2989\nDenver, CO\n\u2022\nVisible Red Rocks Unpaused:\nAdweek, Shorty's, The Drum,\nDenver50, One Club\n\u2022\nVisible #Phonetopia:\nDenver50, One Club\n\u2022\nVisible 404 Stores: Cannes\nLions shortlist, One Club\n\u2022\nStarbucks K-Cup \u201cFlavor\nMatch\u201d, Pro Award\n\u2022\nSeattle's Best Co\ufb00ee \u201cIt\u2019s like a\nfree upgrade\u201d, Silver\nInternationalist Awards\nAWARDS & RECOGNITION\n\u2022\nRelationship building\n\u2022\nFinancial management\n\u2022\nTeam building & leadership\n\u2022\nStrategic brand planning\n\u2022\nComms & creative strategy\n\u2022\nDigital & social innovation\n\u2022\nPaid media & measurement\n\u2022\nCPG & beverage\n\u2022\nShopper & retail marketing\n\u2022\nPromotional & event\nmarketing\n\u2022\nStrong written & verbal\ncommunications\nSKILLS & EXPERTISE\n\u2022\nIn just 90 days restored the health of our largest account and negotiated our FY19\nretainer which more than doubled revenue. Our relationship still remains strong.\n\u2022\nManaging a total client portfolio of +$20MM and driving ~20% organic growth annually.\n\u2022\nMentor and support in career development for an account team of +5 FTEs.\n\u2022\nLed several innovative and award-winning immersive events including Red Rocks\nUnPaused, Unlimited Massages, #InVisibleNY, SXSW Music Box and #Phonetopia.\nS U M M A R Y\nA passionate and driven business leader with over 15 years of integrated marketing and\nbrand building experience, seeking a management position that allows me to inspire a\nmotivated team and drive growth and innovation for a brand.\nP R O F E S S I O N A L E X P E R I E N C E\nGroup Account Director\nMadwell, Denver, CO\nJune 2018 \u2013 Present\nIntegrated Brand & Digital Marketing, Visible Wireless\nResponsible for leading and growing Visible, a newly launched brand and wireless\ncarrier backed by Verizon.\nResponsible for oversight of national CPG campaign initiatives, scope negotiation, revenue\nand sta\ufb03ng for Starbucks, Seattle\u2019s Best Co\ufb00ee and TAZO ($8MM annual revenue).\n\u2022\nGrew our retained agency fee by 37% and delivered against 100% of organic revenue\ngoals 4 years in a row (+$250k/year) through proactive selling.\n\u2022\nManaged professional development for 6 direct reports, negotiated annual scoping and\nsta\ufb03ng for 35 FTEs, and ensured ongoing team health and training.\n\u2022\nLed national integrated product launch of Starbucks Hot Cocoa K-Cups campaign\nincluding TV, print, web, DM sampling, digital media and social in\ufb02uencer activation.\n\u2022\nLed the last \ufb01ve Starbucks seasonal marketing initiatives, of which Holiday FY\u201917 was\nhistorically the highest performing program to date, resulting in 97% ACV.\n\u2022\nAccount lead on SBC qualitative consumer research, brand re-positioning, brand site\nredesign and development, social content strategy, e-CRM and in\ufb02uencer\nprogramming.\nGroup Account Director\nThe Integer Group\nOct 2014 \u2013 June 2018\nIntegrated CPG Marketing, Starbucks and Seattle\u2019s Best Co\ufb00ee\n\u2022\nPioneered the MillerCoors \u201cDigital Toolbox\u201d\u2013an arsenal of digital programs that were\ntested and standardized for customization across the business.\n\u2022\nLaunched the \ufb01rst Food and Beer pairing website for MillerCoors,\nPintsandPlates.com\u2013named MillerCoors program of the year.\n\u2022\nPiloted a motion-activated retail display leading to a 15% lift in o\ufb00-premise beer sales.\n\u2022\nLaunched an NFL test campaign for Miller Lite in partnership with Drizly alcohol delivery.\n\u2022\nSuccessfully activated the Miami Heat Fancam social experience\u2013a \ufb01rst for MillerCoors.\nDigital Innovations Director The Integer Group\nSept 2012 \u2013 Oct 2014\nBRAND PARTNERS\nDelivered integrated program planning, digital media execution, creative development\nand cross-agency integration. In just 2 years, established a digital brand presence that was\nheld up as the \u201cgold standard\u201d at MillerCoors.\n\u2022\nLed the UX, design and launch of the brand\u2019s \ufb01rst mobile optimized site.\n\u2022\nLed a fully integrated award-winning program, \"Craft the Next Blue Moon\", to launch a\nnew consumer-generated \ufb02avor.\n\u2022\nEstablished the strategic approach and social voice for the brand, growing our Facebook\nfans from 40,000 to 400,000+ in under a year.\nAccount Supervisor\nThe Integer Group\nJan 2009 \u2013 Sept 2012\nIntegrated Digital Marketing, Blue Moon Brewing Company\nTest and Learn digital/retail Marketing, MillerCoors portfolio\n\nNATALIE ROSS\nN\nR\nNatRoss14@gmail.com\n314.566.2989\nDenver, CO\nA LITTLE ABOUT ME\nI landed in Colorado just 90\ndays after an amazing\nexperience at the Estes Park\nYoga Conference. I\u2019ll take any\nchance I have to enjoy the\noutdoors; camping,\nhiking, biking, skiing or \ufb01shing.\nA 20 year vegetarian, I enjoy\ncooking and experimenting\nwith new recipes (chopping\nvegetables is like meditation\nfor me). Fun fact: I once made\nthe Denver roller derby team.\nP R O F E S S I O N A L E X P E R I E N C E\n\u2022\nManaged AT&T Small Business Advisory Panels; focus group recruitment, discussion\nguides and research readouts.\n\u2022\nOversaw national print, radio and digital media for AT&T Small Business.\nAccount Supervisor\nRodgers Townsend/DDB\nApril \u2013 Dec 2008\n\u2022\nManaged a team of three after just four years of experience, received three promotions\nwithin five years and worked remotely as a Comcast Marketing Brand Manager.\n\u2022\nLed national campaigns for AB InBev, including Bass Ale, Czechvar and Land Shark Lager.\n\u2022\nProduced and hosted on-site event activation of Comcast/Clear Channel sponsorship at\n13 concert venues and 150 events.\n\u2022\nCo-managed national promotions for International Truck & Engine including celebrity tie-\nins, direct mail, dealer POS and interactive sweepstakes and ful\ufb01llment.\nAccount Manager Momentum Worldwide July 2003 \u2013 April 2008\nBachelor of\nJournalism/Advertising,\nUniversity of Missouri-Columbia,\nSchool of Journalism\nMagna Cum Laude\nEDUCATION", "state": " CO", "resume_key": 9991, "dataset_version": "v1", "years_experience": 4, "education": "", "skills": ["EXPERTISE", "UnPaused", "Unlimited Massages", "#InVisibleNY", "SXSW Music Box", "#Phonetopia", "S U M M A R Y", "A passionate", "brand building experience", "drive growth", "innovation for a brand", "Group Account Director", "Madwell", "Denver", "CO", "Integrated Brand & Digital Marketing", "Visible Wireless", "Responsible for leading", "growing Visible", "a newly launched brand", "wireless carrier backed by Verizon", "scope negotiation", "revenue", "sta\ufb03ng for Starbucks", "Seattle\u2019s Best Co\ufb00ee", "TAZO ($8MM annual revenue)", "goals 4 years in a row", "year) through proactive selling", "Managed professional development for 6 direct reports", "negotiated annual scoping", "sta\ufb03ng for 35 FTEs", "ensured ongoing team health", "training", "TV", "print", "web", "DM sampling", "digital media", "social in\ufb02uencer activation", "resulting in 97% ACV", "Account lead on SBC qualitative consumer research", "brand re-positioning", "brand site redesign", "development", "social content strategy", "e-CRM", "in\ufb02uencer programming", "The Integer Group", "Integrated CPG Marketing", "Starbucks", "Launched the \ufb01rst Food", "Beer pairing website for MillerCoors", "PintsandPlates.com-named MillerCoors program of the year", "Digital Innovations Director The Integer Group", "BRAND PARTNERS", "Delivered integrated program planning", "digital media execution", "creative development", "cross-agency integration. In just 2 years", "Led the UX", "design", "Led a fully integrated award-winning program", "\"Craft the Next Blue Moon\"", "to launch a new consumer-generated \ufb02avor", "Established the strategic approach", "social voice for the brand", "growing our Facebook fans from 40", "000+ in under a year", "Account Supervisor", "Integrated Digital Marketing", "Blue Moon Brewing Company", "Test", "Learn digital", "retail Marketing", "MillerCoors portfolio", "NATALIE ROSS", "A LITTLE ABOUT ME", "I landed in Colorado just 90", "days after an amazing"], "skills_by_category": {"Skills": ["EXPERTISE", "UnPaused", "Unlimited Massages", "#InVisibleNY", "SXSW Music Box", "#Phonetopia", "S U M M A R Y", "A passionate", "brand building experience", "drive growth", "innovation for a brand", "Group Account Director", "Madwell", "Denver", "CO", "Integrated Brand & Digital Marketing", "Visible Wireless", "Responsible for leading", "growing Visible", "a newly launched brand", "wireless carrier backed by Verizon", "scope negotiation", "revenue", "sta\ufb03ng for Starbucks", "Seattle\u2019s Best Co\ufb00ee", "TAZO ($8MM annual revenue)", "goals 4 years in a row", "year) through proactive selling", "Managed professional development for 6 direct reports", "negotiated annual scoping", "sta\ufb03ng for 35 FTEs", "ensured ongoing team health", "training", "TV", "print", "web", "DM sampling", "digital media", "social in\ufb02uencer activation", "resulting in 97% ACV", "Account lead on SBC qualitative consumer research", "brand re-positioning", "brand site redesign", "development", "social content strategy", "e-CRM", "in\ufb02uencer programming", "The Integer Group", "Integrated CPG Marketing", "Starbucks", "Launched the \ufb01rst Food", "Beer pairing website for MillerCoors", "PintsandPlates.com-named MillerCoors program of the year", "Digital Innovations Director The Integer Group", "BRAND PARTNERS", "Delivered integrated program planning", "digital media execution", "creative development", "cross-agency integration. In just 2 years", "Led the UX", "design", "Led a fully integrated award-winning program", "\"Craft the Next Blue Moon\"", "to launch a new consumer-generated \ufb02avor", "Established the strategic approach", "social voice for the brand", "growing our Facebook fans from 40", "000+ in under a year", "Account Supervisor", "Integrated Digital Marketing", "Blue Moon Brewing Company", "Test", "Learn digital", "retail Marketing", "MillerCoors portfolio", "NATALIE ROSS", "A LITTLE ABOUT ME", "I landed in Colorado just 90", "days after an amazing"]}, "experience": [{"title": "", "company": "Rodgers Townsend/DDB", "duration": "Dec 2008", "impact_bullets": ["-", "Managed a team of three after just four years of experience, received three promotions within five years and worked remotely as a Comcast Marketing Brand Manager.", "-", "Led national campaigns for AB InBev, including Bass Ale, Czechvar and Land Shark Lager.", "-", "Produced and hosted on-site event activation of Comcast/Clear Channel sponsorship at", "13 concert venues and 150 events.", "-", "Co-managed national promotions for International Truck & Engine including celebrity tieins, direct mail, dealer POS and interactive sweepstakes and ful\ufb01llment."]}, {"title": "Account Manager Momentum Worldwide", "company": "Bachelor of", "duration": "July 2003 - April 2008", "impact_bullets": ["Journalism/Advertising, University of Missouri-Columbia, School of Journalism", "Magna Cum Laude"]}], "projects": [], "certifications": [], "clearances_or_work_auth": ""}
